diceomatic/__init__.py
diceomatic-0.1.0.dist-info/METADATA
diceomatic-0.1.0.dist-info/WHEEL
diceomatic-0.1.0.dist-info/RECORD
