Metadata-Version: 2.4
Name: diceomatic
Version: 0.1.0
Summary: A DSL for children's dice games and maths quizzes.
Project-URL: Homepage, https://github.com/robert/diceomatic
Project-URL: Repository, https://github.com/robert/diceomatic
Author-email: Robert Heaton <robqheaton@gmail.com.com>
Requires-Python: >=3.8
Provides-Extra: dev
Requires-Dist: pytest>=7.0.0; extra == 'dev'
